chromeAPI/__init__.py
chromeAPI/chromeAPI.py
chromeAPI/main.py
chromeAPI-0.2.2.dist-info/METADATA
chromeAPI-0.2.2.dist-info/WHEEL
chromeAPI-0.2.2.dist-info/top_level.txt
chromeAPI-0.2.2.dist-info/RECORD
